stripy/_ssrfpack.cpython-310-x86_64-linux-gnu.so
stripy/_tripack.cpython-310-x86_64-linux-gnu.so
stripy/_srfpack.cpython-310-x86_64-linux-gnu.so
stripy/spherical.py
stripy/hybrid_st_meshes.py
stripy/__init__.py
stripy/_fortran.cpython-310-x86_64-linux-gnu.so
stripy/_stripack.cpython-310-x86_64-linux-gnu.so
stripy/cartesian.py
stripy/cartesian_meshes.py
stripy/documentation.py
stripy/spherical_meshes.py
stripy/tests/test_sTriangulation.py
stripy/tests/test_1c_warped_xy_meshes.py
stripy/tests/test_Triangulation.py
stripy/tests/test_routines.py
stripy/tests/test_0_imports.py
stripy/tests/test_1b_cartesian_mesh_examples.py
stripy/tests/test_1a_spherical_mesh_examples.py
stripy/tests/__pycache__/test_sTriangulation.cpython-39-pytest-7.4.3.pyc
stripy/tests/__pycache__/test_1a_spherical_mesh_examples.cpython-37-pytest-7.4.3.pyc
stripy/tests/__pycache__/test_0_imports.cpython-38-pytest-7.4.3.pyc
stripy/tests/__pycache__/test_1b_cartesian_mesh_examples.cpython-38-pytest-7.4.3.pyc
stripy/tests/__pycache__/test_1a_spherical_mesh_examples.cpython-38-pytest-7.4.3.pyc
stripy/tests/__pycache__/test_Triangulation.cpython-37-pytest-7.4.3.pyc
stripy/tests/__pycache__/test_Triangulation.cpython-38-pytest-7.4.3.pyc
stripy/tests/__pycache__/test_1a_spherical_mesh_examples.cpython-39-pytest-7.4.3.pyc
stripy/tests/__pycache__/test_1b_cartesian_mesh_examples.cpython-37-pytest-7.4.3.pyc
stripy/tests/__pycache__/test_1c_warped_xy_meshes.cpython-39-pytest-7.4.3.pyc
stripy/tests/__pycache__/test_1c_warped_xy_meshes.cpython-38-pytest-7.4.3.pyc
stripy/tests/__pycache__/test_routines.cpython-39-pytest-7.4.3.pyc
stripy/tests/__pycache__/test_routines.cpython-37-pytest-7.4.3.pyc
stripy/tests/__pycache__/test_0_imports.cpython-39-pytest-7.4.3.pyc
stripy/tests/__pycache__/test_sTriangulation.cpython-37-pytest-7.4.3.pyc
stripy/tests/__pycache__/test_Triangulation.cpython-39-pytest-7.4.3.pyc
stripy/tests/__pycache__/test_0_imports.cpython-37-pytest-7.4.3.pyc
stripy-2.3.3.dist-info/METADATA
stripy-2.3.3.dist-info/RECORD
stripy-2.3.3.dist-info/COPYING.LESSER
stripy-2.3.3.dist-info/WHEEL
