Metadata-Version: 2.1
Name: stripy
Version: 2.3.3
Summary: Python interface to TRIPACK and STRIPACK fortran code for triangulation/interpolation in Cartesian coordinates and on a sphere
Keywords: triangulation sphere interpolation mesh
Author-Email: Louis Moresi <louis.moresi@anu.edu.au>, Ben Mather <ben.mather@sydney.edu.au>
Maintainer-Email: Louis Moresi <louis.moresi@anu.edu.au>, Ben Mather <ben.mather@sydney.edu.au>
License:                    GNU LESSER GENERAL PUBLIC LICENSE
Classifier: Programming Language :: Python
Classifier: Programming Language :: Python :: 3
Classifier: Programming Language :: Python :: 3.7
Classifier: Programming Language :: Python :: 3.8
Classifier: Programming Language :: Python :: 3.9
Classifier: Programming Language :: Python :: 3.10
Classifier: Programming Language :: Python :: 3.11
Classifier: Programming Language :: Python :: 3.12
Project-URL: Homepage, https://github.com/underworldcode/stripy
Requires-Python: >=3.7
Requires-Dist: numpy>=1.16.0
Requires-Dist: pip-tools; extra == "dev"
Requires-Dist: pytest; extra == "dev"
Requires-Dist: scipy>=1.0.0; extra == "dev"
Provides-Extra: dev
